Metadata-Version: 1.1
Name: alibabacloud-openapi-util-py2
Version: 0.0.7
Summary: Aliyun Tea OpenApi Library for Python2
Home-page: https://github.com/aliyun/darabonba-openapi-util
Author: Alibaba Cloud
Author-email: alibaba-cloud-sdk-dev-team@list.alibaba-inc.com
License: Apache License 2.0
Keywords: alibabacloud_openapi_util
Platform: any
Classifier: Development Status :: 4 - Beta
Classifier: Intended Audience :: Developers
Classifier: License :: OSI Approved :: Apache Software License
Classifier: Programming Language :: Python
Classifier: Programming Language :: Python :: 2
Classifier: Programming Language :: Python :: 2.7
Classifier: Topic :: Software Development
